{"results":[{"protectionRegionCode":"33","protectionRegion":"Polska","priorityExhibitionNumber":null,"grantingInstitutionCode":"3","applicationNumber":"130322","plantBotanicName":null,"inventors":[{"relatedInstitutionUuid":"d8a6d07c-521d-4ddd-a94a-77e57721861a","relatedInstitutionName":"Centrum Badań i Innowacji Pro-Akademia","persons":[{"employeeId":null,"firstName":"Maksymilian","relatedFirstName":null,"middleName":null,"relatedMiddleName":null,"lastName":"Kochański","relatedLastName":null,"relatedOrcid":null,"evaluationStatement":[]},{"employeeId":null,"firstName":"Łukasz","relatedFirstName":null,"middleName":null,"relatedMiddleName":null,"lastName":"Gontar","relatedLastName":null,"relatedOrcid":null,"evaluationStatement":[]},{"employeeId":null,"firstName":"Maria","relatedFirstName":null,"middleName":null,"relatedMiddleName":null,"lastName":"Buła","relatedLastName":null,"relatedOrcid":null,"evaluationStatement":[]},{"employeeId":null,"firstName":"Monika","relatedFirstName":null,"middleName":null,"relatedMiddleName":null,"lastName":"Sitarek-Andrzejczyk","relatedLastName":null,"relatedOrcid":null,"evaluationStatement":[]},{"employeeId":null,"firstName":"Dariusz","relatedFirstName":null,"middleName":null,"relatedMiddleName":null,"lastName":"Zych","relatedLastName":null,"relatedOrcid":null,"evaluationStatement":[]},{"employeeId":null,"firstName":"Ewa","relatedFirstName":null,"middleName":null,"relatedMiddleName":null,"lastName":"Kochańska","relatedLastName":null,"relatedOrcid":null,"evaluationStatement":[]}]}],"applicants":[{"relatedInstitutionUuid":"d8a6d07c-521d-4ddd-a94a-77e57721861a","relatedInstitutionName":"Centrum Badań i Innowacji Pro-Akademia","institutions":[{"institutionUuid":null,"institutionName":"Pellets System Sp.z o.o.","higherEducationInstitutionMarker":null,"higherEducationInstitutionName":null},{"institutionUuid":null,"institutionName":"Centrum Badań i Innowacji Pro-Akademia","higherEducationInstitutionMarker":null,"higherEducationInstitutionName":null}]}],"priorityNumber":null,"relatedInstitutions":[{"institutionUuid":"d8a6d07c-521d-4ddd-a94a-77e57721861a","institutionName":"Centrum Badań i Innowacji Pro-Akademia"}],"plantVarietyNames":[],"priorityApplicationNumberUPRP":null,"priorityRegion":null,"plantSpeciesNames":[],"priorityFirstApplication":"true","protectionTitle":"Granula ściółkowa\t","publicationDate":"2023-04-12","grantingInstitutionName":"Urząd Patentowy Rzeczpospolitej Polskiej","dateSubmissionTranslation":null,"protectionTypeCode":"2","productDescription":"Przedmiotem zgłoszenia jest granula ściółkowa w postaci walca o średnicy w zakresie 6 — 8 mm i długości w zakresie 10 — 35 mm, zbudowana ze sprasowanej słomy zbożowej z dodatkiem równomiernie rozproszonych w całej objętości granuli frakcjach cząstek: ususzonego ziela cząbru ogrodowego (Satureja hortensis) o wielkości cząstek w zakresie 0,4 — 5 mm, oraz ususzonego ziela lebiodki pospolitej (Origanum vulgare) o wielkości cząstek w zakresie 0,4 — 6 mm, w proporcji cząstki cząbru ogrodowego: cząstki ziela lebiodki pospolitej od 1: 4 do 6: 1; frakcje cząstek ususzonego ziela cząbru ogrodowego i ususzonego ziela lebiodki pospolitej stanowią łącznie od 1 do 43% suchej masy sprasowanej słomy.","publicationNumber":"073127","productTitles":[{"code":"polski","value":"Granula ściółkowa\t"}],"protectionType":"Prawo ochronne na wzór użytkowy","protectionUuid":"16E5E344DB942B4705E2FCED6BBA0AD1","lastRefresh":"1747037860851","priorityClaimDate":null,"grantingInstitutionCountry":null,"dataSource":"POLON","applicationDate":"2021-10-12"},{"protectionRegionCode":"33","protectionRegion":"Polska","priorityExhibitionNumber":null,"grantingInstitutionCode":"3","applicationNumber":"438297","plantBotanicName":null,"inventors":[{"relatedInstitutionUuid":"d8a6d07c-521d-4ddd-a94a-77e57721861a","relatedInstitutionName":"Centrum Badań i Innowacji Pro-Akademia","persons":[{"employeeId":null,"firstName":"MARCIN","relatedFirstName":null,"middleName":null,"relatedMiddleName":null,"lastName":"SIEDLECKI","relatedLastName":null,"relatedOrcid":null,"evaluationStatement":[]},{"employeeId":null,"firstName":"RAFAŁ","relatedFirstName":null,"middleName":null,"relatedMiddleName":null,"lastName":"MAJZER","relatedLastName":null,"relatedOrcid":null,"evaluationStatement":[]}]}],"applicants":[{"relatedInstitutionUuid":"d8a6d07c-521d-4ddd-a94a-77e57721861a","relatedInstitutionName":"Centrum Badań i Innowacji Pro-Akademia","institutions":[{"institutionUuid":null,"institutionName":"CENTRUM BADAŃ I INNOWACJI PRO-AKADEMIA","higherEducationInstitutionMarker":null,"higherEducationInstitutionName":null},{"institutionUuid":null,"institutionName":"SERAFIN WŁODZIMIERZ PRZEDSIĘBIORSTWO TECHNICZNO HANDLOWE WODPOL","higherEducationInstitutionMarker":null,"higherEducationInstitutionName":null}]}],"priorityNumber":null,"relatedInstitutions":[{"institutionUuid":"d8a6d07c-521d-4ddd-a94a-77e57721861a","institutionName":"Centrum Badań i Innowacji Pro-Akademia"}],"plantVarietyNames":[],"priorityApplicationNumberUPRP":null,"priorityRegion":null,"plantSpeciesNames":[],"priorityFirstApplication":"true","protectionTitle":"Układ do półautomatycznego pomiaru parametru Slit Density Index (SDI) dla próbek bezciśnieniowych","publicationDate":"2024-02-26","grantingInstitutionName":"Urząd Patentowy Rzeczpospolitej Polskiej","dateSubmissionTranslation":null,"protectionTypeCode":"1","productDescription":"Sposób półautomatycznego pomiaru parametru Slit Density Index (SDI) dla próbek bezciśnieniowych charakteryzuje się tym, że po wyzwoleniu przyciskiem 'napełnianie' na ekranie panelu dotykowego jednostki sterującej (1) poprzez otwarcie elektrozaworu odpowietrzającego (4) oraz otwarcie elektrozaworu (6) następuje wypełnienie zbiornika głównego (7) badaną próbką cieczy, po napełnieniu zbiornika głównego (7) następuje zmiana stanu czujnika poziomu cieczy (8) na 'zbiornik napełniony' i zamknięcie zaworu (6) doprowadzenia próbki oraz zamknięcie zaworu odpowietrzającego (4) w dalszej kolejności następuje ręczny montaż filtra (11) a następnie po wyzwoleniu przyciskiem 'start' na ekranie panelu dotykowego jednostki sterującej (1) poprzez otwarcie elektrozaworu (10) oraz otwarcie elektrozaworu (3) poprzez precyzyjny regulator ciśnienia (2) ustalane jest ciśnienie w zbiorniku głównym (7) w przedziale od 2.0 — 2.1 bar w dalszej kolejności po osiągnięciu zadanego ciśnienia mierzonego czujnikiem ciśnienia (9) następuje otwarcie elektrozaworu (12) zbiornika kalibrowanego nr 1 (17) i napełnianie go cieczą przy jednoczesnym automatycznym pomiarze czasu t0 za pomocą licznika czasu wbudowanego w jednostkę sterującą (1) aż do zmiany stanu czujnika (15) poziomu cieczy na 'zbiornik napełniony’, po czym następuje zamknięcie elektrozaworu (12) zbiornika kalibrowanego nr 1 (17), otwarcie elektrozaworu zrzutu (13) na czas 15 minut, po tym czasie następuje zamknięcie elektrozaworu zrzutu (13) i otwarcie elektrozaworu (14) zbiornika kalibrowanego nr 2 (18), którego czas t15 napełniania cieczą mierzony jest za pomocą licznika czasu wbudowanego w jednostkę sterującą (1), aż do zmiany stanu czujnika (16) poziomu cieczy na 'zbiornik napełniony', po napełnieniu zbiornika kalibrowanego nr 2 (18) następuje zamknięcie elektrozaworu (14). Kolejno następuje zamknięcie elektrozaworu (10) oraz otwarcie elektrozaworu odpowietrzającego (4). Przeliczony wynik pomiaru parametru Slit Density Index (SDI) wyświetlany jest na ekranie jednostki sterującej (1).","publicationNumber":"244698","productTitles":[{"code":"polski","value":"Układ do półautomatycznego pomiaru parametru Slit Density Index (SDI) dla próbek bezciśnieniowych"},{"code":"angielski","value":"Method of semi-automatic measurement of the Slit Density Index (SDI) parameter for non-pressure samples and system for semi-automatic measurement of the Slit Density Index (SDI) parameter for non-pressure samples"}],"protectionType":"Patent na wynalazek","protectionUuid":"9DEADC793F48ED651EB9D0A37ED99AD7","lastRefresh":"1747038555634","priorityClaimDate":null,"grantingInstitutionCountry":null,"dataSource":"POLON","applicationDate":"2021-06-29"}],"pagination":{"maxCount":2,"token":"MTc0NzAzODU1NTYzNA=="},"version":"1.1.7"}